cellment/__init__.py
cellment/background.py
cellment/functions.py
cellment/segmentation.py
cellment/tracking.py
cellment/wavelets.py
cellment-0.1.0.dist-info/LICENSE
cellment-0.1.0.dist-info/METADATA
cellment-0.1.0.dist-info/WHEEL
cellment-0.1.0.dist-info/top_level.txt
cellment-0.1.0.dist-info/RECORD
